django_bandits/__init__.py
django_bandits/admin.py
django_bandits/apps.py
django_bandits/forms.py
django_bandits/middleware.py
django_bandits/migrations/0001_squashed_0004_remove_epsilondecaymodel_beta.py
django_bandits/migrations/0005_banditflag_ignore_for_authenticated_users.py
django_bandits/migrations/__init__.py
django_bandits/models.py
django_bandits-0.1.6.dist-info/LICENSE
django_bandits-0.1.6.dist-info/METADATA
django_bandits-0.1.6.dist-info/WHEEL
django_bandits-0.1.6.dist-info/RECORD
