Metadata-Version: 2.1
Name: django-bandits
Version: 0.1.6
Summary: A package enabling multi-armed bandits for site optimization and Django.
Home-page: https://github.com/hubbs5/django-bandits
License: Apache 2.0
Author: Christian
Author-email: christiandhubbs@gmail.com
Requires-Python: >=3.8,<3.13
Classifier: Development Status :: 3 - Alpha
Classifier: Framework :: Django
Classifier: Intended Audience :: Developers
Classifier: License :: Other/Proprietary License
Classifier: Programming Language :: Python
Classifier: Programming Language :: Python :: 3
Classifier: Programming Language :: Python :: 3.8
Classifier: Programming Language :: Python :: 3.9
Classifier: Programming Language :: Python :: 3.10
Classifier: Programming Language :: Python :: 3.11
Classifier: Topic :: Software Development :: Libraries :: Python Modules
Classifier: Topic :: Software Development :: Testing
Requires-Dist: django (>=3.2,<5.0)
Requires-Dist: django-waffle (>=4.0.0,<5.0.0)
Requires-Dist: numpy (>=1.18,<2.0)
Requires-Dist: scipy (>=1.7,<=1.11.2)
